packageobf/__init__.py
packageobf/one.py
packageobf-0.2.dist-info/METADATA
packageobf-0.2.dist-info/WHEEL
packageobf-0.2.dist-info/top_level.txt
packageobf-0.2.dist-info/RECORD
