Metadata-Version: 2.1
Name: packageobf
Version: 0.2
Summary: This is code with package
Home-page: UNKNOWN
Author: jitu
License: UNKNOWN
Platform: UNKNOWN
